Metadata-Version: 2.1
Name: eidos
Version: 1.1.2
Summary: Modelling primary beams of radio telescope antennae
Home-page: https://github.com/ratt-ru/eidos
Author: Khan M. B Asad
Author-email: khmbasad@gmail.com
License: GNU GPL v3
Classifier: Development Status :: 3 - Alpha
Classifier: Intended Audience :: Science/Research
Classifier: License :: OSI Approved :: GNU General Public License v3 (GPLv3)
Classifier: Operating System :: POSIX :: Linux
Classifier: Programming Language :: Python
Classifier: Topic :: Scientific/Engineering :: Astronomy
Requires-Dist: numpy
Requires-Dist: scipy
Requires-Dist: astropy
Requires-Dist: future
